datatypeplus/__init__.py
datatypeplus/flow.py
datatypeplus-1.1.1.dist-info/licenses/LICENSE.TXT
datatypeplus-1.1.1.dist-info/METADATA
datatypeplus-1.1.1.dist-info/WHEEL
datatypeplus-1.1.1.dist-info/top_level.txt
datatypeplus-1.1.1.dist-info/RECORD
