Metadata-Version: 2.4
Name: datatypeplus
Version: 1.1.1
Summary: A lightweight Python library for flexible data structures and reactive lists.
Author: Prayaan Sharma
Author-email: prayaansharma@gmail.com
License: MIT
Classifier: Programming Language :: Python :: 3
Classifier: License :: OSI Approved :: MIT License
Classifier: Operating System :: OS Independent
Requires-Python: >=3.8
License-File: LICENSE.TXT
Dynamic: author
Dynamic: author-email
Dynamic: classifier
Dynamic: description
Dynamic: description-content-type
Dynamic: license
Dynamic: license-file
Dynamic: requires-python
Dynamic: summary
